ingenii_data_engineering/__init__.py
ingenii_data_engineering/__main__.py
ingenii_data_engineering/dbt_schema.py
ingenii_data_engineering/pre_process.py
ingenii_data_engineering/split_xlsx.py
ingenii_data_engineering-0.3.3.dist-info/LICENSE
ingenii_data_engineering-0.3.3.dist-info/METADATA
ingenii_data_engineering-0.3.3.dist-info/WHEEL
ingenii_data_engineering-0.3.3.dist-info/dependency_links.txt
ingenii_data_engineering-0.3.3.dist-info/top_level.txt
ingenii_data_engineering-0.3.3.dist-info/RECORD
