Metadata-Version: 2.1
Name: ingenii-data-engineering
Version: 0.3.3
Summary: Facilitate data engineering on the Ingenii Data Platform
Home-page: https://github.com/ingenii-solutions/azure-data-platform-data-engineering
Author: Greg Atkins
Author-email: greg@ingenii.dev
License: UNKNOWN
Platform: UNKNOWN
Classifier: Programming Language :: Python :: 3
Classifier: License :: OSI Approved :: Mozilla Public License 2.0 (MPL 2.0)
Classifier: Operating System :: OS Independent
License-File: LICENSE
Requires-Dist: openpyxl==3.0.7
Requires-Dist: wheel>=0.36.2
